{
  "foods": [
    {
      "id": 3,
      "name": "A la Camarón aaa",
      "description": "Macarrão com vegetais de primeira linha e camarão dos 7 mares.",
      "price": "25.90",
      "available": false,
      "image": "https://storage.googleapis.com/golden-wind/bootcamp-gostack/desafio-food/food3.png"
    },
    {
      "image": "fdgdsgrdsg",
      "name": "dfgfdfdgdf",
      "price": "222464564",
      "description": "sfdgafhnftnf",
      "available": true,
      "id": 4
    },
    {
      "image": "sdlidjgsd",
      "name": "dsdgsd",
      "price": "333",
      "description": "fgdfgdb",
      "available": true,
      "id": 5
    },
    {
      "image": "fgn",
      "name": "fgnfg",
      "price": "433",
      "description": "dfgbgb",
      "available": true,
      "id": 6
    },
    {
      "image": "b gf",
      "name": "gbgf",
      "price": "43r",
      "description": "fdbfd",
      "available": true,
      "id": 7
    }
  ]
}